ldis/__init__.py
ldis/config.py
ldis/fastscript.py
ldis-0.0.1.dist-info/LICENSE
ldis-0.0.1.dist-info/METADATA
ldis-0.0.1.dist-info/WHEEL
ldis-0.0.1.dist-info/entry_points.txt
ldis-0.0.1.dist-info/top_level.txt
ldis-0.0.1.dist-info/RECORD
