Metadata-Version: 2.1
Name: ldis
Version: 0.0.1
Summary: Local dictionary server.
Home-page: https://github.com/polyrand
Author: Ricardo Ander-Egg Aguilar
Author-email: ricardo.anderegg@gmail.com
License: UNKNOWN
Platform: UNKNOWN
Classifier: Development Status :: 2 - Pre-Alpha
Classifier: License :: OSI Approved :: MIT License
Classifier: Operating System :: OS Independent
Classifier: Programming Language :: Python :: 3
Classifier: Programming Language :: Python :: 3 :: Only
Classifier: Programming Language :: Python :: 3.7
Classifier: Programming Language :: Python :: 3.8
Requires-Python: >=3.7
